{
  "type": "opensaberLayoutSchema",
  "version": "0.1",
  "forms": [
    {
      "prerak-signup": {
        "api": "/PrerakV2/invite",
        "type": "entity",
        "formclass": "row",
        "header": "default2",
        "title": "Create Profile",
        "isSignupForm": "true",
        "langKey": "prerakAdmin",
        "fieldsets": [
          {
            "definition": "PrerakV2",
            "fields": [
              {
                "name": "fullName",
                "required": true,
                "validation": {
                  "message": "NAME_NOT_VALID"
                }
              },
              {
                "name": "mobile",
                "required": true,
                "validation": {
                  "pattern": "[1-9]{1}[0-9]{9}",
                  "message": "MOBILE_NO_MUST_10_DIGIT"
                }
              },
              {
                "name": "qualification"
              },
              {
                "name": "gender"
              },
              {
                "name": "age"
              },
              {
                "name": "address",
                "children": {
                  "definition": "Address",
                  "title": false,
                  "fields": [
                    {
                      "name": "district",
                      "dependent": {
                        "key": "district",
                        "title": "District",
                        "type": "select",
                        "options": "this.locationService.getDistrict()"
                      }
                    }
                  ]
                }
              },
              {
                "name": "sourcingChannel"
              },
              {
                "name": "referrerIfApplicable"
              },
              {
                "name": "referenceId"
              },
              {
                "name": "relationshipWithTheCandidate"
              },
              {
                "name": "parentOrganization"
              }
            ]
          }
        ],
        "redirectTo": "/profile/prerakv2"
      }
    },
    {
      "prerak-setup": {
        "api": "/PrerakV2",
        "type": "entity",
        "redirectTo": "/profile/prerakv2",
        "langKey": "prerakAdmin",
        "fieldsets": [
          {
            "definition": "PrerakV2",
            "privacyConfig": "PrerakV2OsConfig",
            "globalPrivacyConfig": "internal-access",
            "fields": [
              {
                "name": "fullName",
                "required": true,
                "validation": {
                  "message": "NAME_NOT_VALID"
                }
              },
              {
                "name": "mobile",
                "required": true,
                "validation": {
                  "pattern": "[1-9]{1}[0-9]{9}",
                  "message": "MOBILE_NO_MUST_10_DIGIT"
                }
              },
              {
                "name": "qualification"
              },
              {
                "name": "gender"
              },
              {
                "name": "age"
              },
              {
                "name": "address",
                "children": {
                  "definition": "Address",
                  "title": false,
                  "fields": [
                    {
                      "name": "district",
                      "dependent": {
                        "key": "district",
                        "title": "District",
                        "type": "select",
                        "options": "this.locationService.getDistrict()"
                      }
                    }
                  ]
                }
              },
              {
                "name": "sourcingChannel"
              },
              {
                "name": "referrerIfApplicable"
              },
              {
                "name": "referenceId"
              },
              {
                "name": "relationshipWithTheCandidate"
              },
              {
                "name": "parentOrganization"
              }
            ]
          }
        ]
      }
    },
    {
      "prerak-admin-setup": {
        "api": "/PrerakV2",
        "type": "entity",
        "redirectTo": "profile/admin-prerak",
        "langKey": "prerakAdmin",
        "fieldsets": [
          {
            "definition": "PrerakV2",
            "privacyConfig": "PrerakV2OsConfig",
            "globalPrivacyConfig": "internal-access",
            "fields": [
              {
                "name": "fullName",
                "required": true,
                "validation": {
                  "message": "NAME_NOT_VALID"
                }
              },
              {
                "name": "mobile",
                "required": true,
                "validation": {
                  "pattern": "[1-9]{1}[0-9]{9}",
                  "message": "MOBILE_NO_MUST_10_DIGIT"
                }
              },
              {
                "name": "qualification"
              },
              {
                "name": "gender"
              },
              {
                "name": "age"
              },
              {
                "name": "address",
                "children": {
                  "definition": "Address",
                  "title": false,
                  "fields": [
                    {
                      "name": "district",
                      "dependent": {
                        "key": "district",
                        "title": "District",
                        "type": "select",
                        "options": "this.locationService.getDistrict()"
                      }
                    }
                  ]
                }
              },
              {
                "name": "sourcingChannel"
              },
              {
                "name": "referrerIfApplicable"
              },
              {
                "name": "referenceId"
              },
              {
                "name": "relationshipWithTheCandidate"
              },
              {
                "name": "parentOrganization"
              },
              {
                "name": "candidateStatus"
              },
              {
                "name": "vfsMemberName"
              },
              {
                "name": "numberOfAttempts"
              },
              {
                "name": "callStatus"
              },
              {
                "name": "explainRROfPrerak"
              },
              {
                "name": "userInterestedRole"
              },
              {
                "name": "reasonForNotInterested"
              },
              {
                "name": "descForNotInterested"
              },
              {
                "name": "confirmName"
              },
              {
                "name": "confirmPhoneNumber",
                "validation": {
                  "pattern": "[1-9]{1}[0-9]{9}",
                  "message": "MOBILE_NO_MUST_10_DIGIT"
                }
              },
              {
                "name": "confirmQualification"
              },
              {
                "name": "accessToMobNo"
              },
              {
                "name": "confirmAddress",
                "children": {
                  "definition": "Address",
                  "title": false,
                  "fields": [
                    {
                      "name": "district",
                      "dependent": {
                        "key": "district",
                        "title": "District",
                        "type": "select",
                        "options": "this.locationService.getDistrict()"
                      }
                    },
                    {
                      "name": "block",
                      "dependent": {
                        "key": "block",
                        "title": "Block",
                        "type": "select",
                        "options": "this.locationService.getBlock()"
                      }
                    },
                    {
                      "name": "village",
                      "dependent": {
                        "key": "village",
                        "title": "Village",
                        "type": "select",
                        "options": "this.locationService.getVillage()"
                      }
                    }
                  ]
                }
              },
              {
                "name": "alternateMobileNumber"
              },
              {
                "name": "whenToCallNextOrOtherNotes"
              }
            ]
          }
        ]
      }
    },

    {
      "prerak-education": {
        "api": "/PrerakV2",
        "type": "property:academicQualifications",
        "redirectTo": "/profile/teacher",
        "langKey": "prerakAdmin",
        "fieldsets": [
          {
            "definition": "AcademicQualification",
            "privacyConfig": "AffiliationOsConfig",
            "fields": [
              {
                "name": "instituteName",
                "required": true,
                "autocomplete": {
                  "apiURL": "https://demo-education-registry.xiv.in/registry/api/v1/Institute/search",
                  "body": {
                    "filters": {
                      "instituteName": {
                        "contains": "{{value}}"
                      },
                      "instituteAffiliation._osState": {
                        "eq": "PUBLISHED"
                      }
                    },
                    "limit": 20,
                    "offset": 0
                  },
                  "responseKey": "instituteName"
                },
                "autofill": {
                  "apiURL": "https://demo-education-registry.xiv.in/registry/api/v1/Institute/search",
                  "method": "POST",
                  "body": {
                    "filters": {
                      "instituteName": {
                        "contains": "{{value}}"
                      },
                      "instituteAffiliation._osStatus": "PUBLISHED"
                    },
                    "limit": 20,
                    "offset": 0
                  },
                  "fields": [
                    {
                      "instituteOSID": "osid"
                    }
                  ]
                }
              },
              {
                "name": "qualification",
                "required": true
              },
              {
                "name": "program"
              },
              {
                "name": "graduationYear",
                "required": true
              },
              {
                "name": "marks"
              }
            ]
          }
        ]
      }
    },
    {
      "teacher-experience": {
        "api": "/PrerakV2",
        "type": "property:experience",
        "redirectTo": "/profile/prerakv2",
        "langKey": "prerakAdmin",
        "fieldsets": [
          {
            "definition": "ExperienceType",
            "privacyConfig": "AffiliationOsConfig",
            "fields": [
              {
                "name": "instituteName",
                "required": true,
                "autocomplete": {
                  "apiURL": "https://demo-education-registry.xiv.in/registry/api/v1/Institute/search",
                  "body": {
                    "filters": {
                      "instituteName": {
                        "contains": "{{value}}"
                      },
                      "instituteAffiliation._osState": {
                        "eq": "PUBLISHED"
                      }
                    },
                    "limit": 20,
                    "offset": 0
                  },
                  "responseKey": "instituteName"
                },
                "autofill": {
                  "apiURL": "https://demo-education-registry.xiv.in/registry/api/v1/Institute/search",
                  "method": "POST",
                  "body": {
                    "filters": {
                      "instituteName": {
                        "contains": "{{value}}"
                      }
                    },
                    "limit": 20,
                    "offset": 0
                  },
                  "fields": [
                    {
                      "instituteOSID": "osid"
                    }
                  ],
                  "dropdowns": [
                    {
                      "grades": "affiliation[0].classes"
                    }
                  ]
                }
              },
              {
                "name": "employmentType",
                "required": true
              },
              {
                "name": "start",
                "required": true,
                "type": "date",
                "validation": {
                  "future": false
                }
              },
              {
                "name": "end",
                "type": "date",
                "validation": {
                  "greaterThan": "start",
                  "message": "END_DATE_GREATER_THAN_START_DATE"
                }
              },
              {
                "name": "teacherType",
                "required": true
              },
              {
                "name": "subjectsTaught",
                "type": "repeat"
              },
              {
                "name": "attest",
                "custom": true,
                "element": {
                  "title": "SEND_FOR_ATTENSTATION",
                  "widget": {
                    "formlyConfig": {
                      "type": "checkbox",
                      "fieldGroupClassName": "controls",
                      "className": "checkbox",
                      "templateOptions": {
                        "required": true
                      }
                    }
                  }
                }
              },
              {
                "name": "notes",
                "custom": true,
                "element": {
                  "title": "NOTE",
                  "widget": {
                    "formlyConfig": {
                      "type": "string",
                      "fieldGroupClassName": "controls",
                      "className": "input",
                      "hideExpression": "!model.attest"
                    }
                  }
                }
              }
            ]
          }
        ]
      }
    },
    {
      "interview": {
        "api": "/PrerakV2",
        "type": "property:interviewDetails",
        "redirectTo": "/profile/admin-prerak/",
        "langKey": "prerakAdmin",
        "fieldsets": [
          {
            "definition": "interviewDetails",
            "privacyConfig": "PrerakV2OsConfig",
            "globalPrivacyConfig": "private-access",
            "fields": [
              {
                "name": "vfsTeamName"
              },
              {
                "name": "mcqWhyDoYouWantPragatiPrerak"
              },
              {
                "name": "freeTextWhyDoYouWantPragatiPrerak"
              },
              {
                "name": "mcqPastExperienceVolunteering"
              },
              {
                "name": "freeTextNgoExperience"
              },
              {
                "name": "mcqYearOfNgoExperience"
              },
              {
                "name": "mcqSectorOfNgoExperience"
              },
              {
                "name": "mcqPrimaryStakeholder"
              },
              {
                "name": "mcqEngagementType"
              },
              {
                "name": "mcqPastTeachingExperience"
              },
              {
                "name": "freeTextTeachingExpierience"
              },
              {
                "name": "mcqYearOfTeachingExpierience"
              },
              {
                "name": "mcqTeachingEngagementType"
              },
              {
                "name": "mcqPrimaryStakeholderType"
              },
              {
                "name": "mcqTrainingExpierience"
              },
              {
                "name": "freeTextTrainingExpierience"
              },
              {
                "name": "mcqTrainingProvider"
              },
              {
                "name": "mcqTrainingDuration"
              },
              {
                "name": "mcqTrainingContent"
              },
              {
                "name": "mcqAnyOtherExperience"
              },
              {
                "name": "freeTextExplainAboutYourExperience"
              },
              {
                "name": "mcqPastExperienceWillHelp"
              },
              {
                "name": "mcqPocPastExperience"
              },
              {
                "name": "freeTextNameOfPoc"
              },
              {
                "name": "digitMobNoOfPoc"
              },
              {
                "name": "mcqRelationshipWithThePOC"
              },
              {
                "name": "interviewDate",
                "format": "date"
              }
            ]
          }
        ]
      }
    },
    {
      "AG-add": {
        "api": "/AGV7",
        "type": "entity",
        "formclass": "row",
        "title": "Add new AG",
        "fieldsets": [
          {
            "definition": "AGV7",
            "dependencies": {
              "mobileAvailablity": {
                "oneOf": [
                  {
                    "properties": {
                      "mobileAvailablity": {
                        "enum": ["हाँ"]
                      },
                      "AGWhatsappNumber": {
                        "type": "string",
                        "title": "कृपया किशोरी के पास उपलब्ध फ़ोन का नंबर दर्ज करें",
                        "validation": {
                          "pattern": "[6-9]{1}[0-9]{9}",
                          "message": "Mobile Number must be 10 digit number."
                        }
                      }
                    }
                  },
                  {
                    "properties": {
                      "mobileAvailablity": {
                        "enum": ["Yes"]
                      }
                    },
                    "required": ["AGWhatsappNumber"]
                  }
                ]
              },
              "mobileAvailablity": {
                "oneOf": [
                  {
                    "properties": {
                      "mobileAvailablity": {
                        "enum": ["हाँ"]
                      },
                      "AGWhatsappNumber": {
                        "type": "string",
                        "title": "कृपया किशोरी के पास उपलब्ध फ़ोन का नंबर दर्ज करें",
                        "validation": {
                          "pattern": "[6-9]{1}[0-9]{9}",
                          "message": "Mobile Number must be 10 digit number."
                        }
                      }
                    }
                  },
                  {
                    "properties": {
                      "mobileAvailablity": {
                        "enum": ["Yes"]
                      }
                    },
                    "required": ["AGWhatsappNumber"]
                  }
                ]
              }
            },
            "fields": [
              {
                "name": "prerakName",
                "custom": true,
                "data": {
                  "type": "api",
                  "url": "/PrerakV2",
                  "key": "fullName"
                },
                "element": {
                  "widget": {
                    "formlyConfig": {
                      "type": "input",
                      "templateOptions": {
                        "type": "hidden"
                      }
                    }
                  }
                }
              },
              {
                "name": "AGfullName",
                "required": true,
                "validation": {
                  "pattern": "^[a-zA-Z]+ [a-zA-Z]+$",
                  "message": "Name is not valid."
              }
              },
              {
                "name": "dob",
                "required": true,
                "type": "date",
                "validation": {
                  "future": false,
                  "max": "2022-09-10",
                  "message": "Please enter a valid date"
                }
              },
              {
                "name": "category",
                "required": true
              },
              {
                "name": "connectVia",
                "required": true
              },
              {
                "name": "fatherFullName",
                "required": true,
                "validation": {
                  "pattern": "^[a-zA-Z]+ [a-zA-Z]+$",
                  "message": "Name is not valid."
              }

              },
              {
                "name": "motherFullName",
                "required": true,
                "validation": {
                  "pattern": "^[a-zA-Z]+ [a-zA-Z]+$",
                  "message": "Name is not valid."
              }
              },
              {
                "name": "parentsMobileNumber",
                "required": true,
                "validation": {
                  "pattern": "[6-9]{1}[0-9]{9}",
                  "message": "Mobile Number must be 10 digit number."
              }
              },
              {
                "name": "sameAsAbove",
                "custom": true,
                "element": {
                    "title": "Same as above?",
                    "widget": {
                        "formlyConfig": {
                            "type": "checkbox",
                            "fieldGroupClassName": "controls",
                            "className": "checkbox",
                            "templateOptions": {
                                "required": true
                            }

                        }
                    }
                }
            },
              {
                "name": "parentsWhatsappNumber",
                "required": true,
                "validation": {
                  "pattern": "[6-9]{1}[0-9]{9}",
                  "message": "Mobile Number must be 10 digit number."
                },
                "expressionProperties": {
                  "templateOptions.disabled": "model.sameAsAbove",
                  "templateOptions.required": "!model.sameAsAbove"
                }
              },
              {
                "name": "mobileAvailablity",
                "required": true
              },

              {
                "name": "lastStandardOfEducation",
                "required": true
              },
              {
                "name": "lastStandardOfEducationYear",
                "required": true,
                "type": "date",
                "validation": {
                  "future": false
                }
              },
              {
                "name": "reasonOfLeavingEducation",
                "required": true
              },
              {
                "name": "whereStudiedLast",
                "required": true
              },
              {
                "name": "registrationStatus",
                "required": true
              },
              {
                "name": "AGDocumentsV2",
                "required": true
              }

            ]
          }
        ],
        "redirectTo": "/profile/myags"
      }
    },
    {
      "ag-setup": {
        "api": "/AGV7",
        "type": "entity",
        "redirectTo": "profile/myags",
        "langKey": "prerakAdmin",
        "fieldsets": [
          {
            "definition": "AGV7",
            "dependencies": {
              "mobileAvailablity": {
                  "oneOf": [
                      {
                          "properties": {
                              "mobileAvailablity": {
                                  "enum": [
                                      "हाँ"
                                  ]
                              },
                              "AGWhatsappNumber": {
                                  "type": "string",
                                  "title": "कृपया किशोरी के पास उपलब्ध फ़ोन का नंबर दर्ज करें",
                                  "validation": {
                                    "pattern": "[6-9]{1}[0-9]{9}",
                                    "message": "Mobile Number must be 10 digit number."
                                }
                              }

                          }
                      },
                      {
                          "properties": {
                              "mobileAvailablity": {
                                  "enum": [
                                      "Yes"
                                  ]
                              }
                          },
                          "required": [
                              "AGWhatsappNumber"
                          ]
                      }
                  ]
              },
              "mobileAvailablity": {
                  "oneOf": [
                      {
                          "properties": {
                              "mobileAvailablity": {
                                  "enum": [
                                      "हाँ"
                                  ]
                              },
                              "AGWhatsappNumber": {
                                  "type": "string",
                                  "title": "कृपया किशोरी के पास उपलब्ध फ़ोन का नंबर दर्ज करें",
                                  "validation": {
                                    "pattern": "[6-9]{1}[0-9]{9}",
                                    "message": "Mobile Number must be 10 digit number."
                                }
                              }

                          }
                      },
                      {
                          "properties": {
                              "mobileAvailablity": {
                                  "enum": [
                                      "Yes"
                                  ]
                              }
                          },
                          "required": [
                              "AGWhatsappNumber"
                          ]
                      }
                  ]
              }
          },
            "fields": [
              {
                  "name": "prerakName",
                  "custom": true,
                  "data": {
                    "type": "api",
                    "url": "/PrerakV2",
                    "key": "fullName"
                  },
                  "element": {
                      "widget": {
                          "formlyConfig": {
                              "type": "input",
                              "templateOptions": {
                                  "type": "hidden"
                              }
                          }
                      }
                  }
              },
              {
                "name": "AGfullName",
                "required": true,
                "validation": {
                  "pattern": "^[a-zA-Z]+ [a-zA-Z]+$",
                  "message": "Name is not valid."
              }
              },
              {
                "name": "dob",
                "required": true,
                "type": "date",
                "validation": {
                  "future": false,
                  "max": "2022-09-10",
                  "message": "Please enter a valid date"
                }
              },
              {
                "name": "category",
                "required": true
              },
              {
                "name": "connectVia",
                "required": true
              },
              {
                "name": "fatherFullName",
                "required": true,
                "validation": {
                  "pattern": "^[a-zA-Z]+ [a-zA-Z]+$",
                  "message": "Name is not valid."
              }

              },
              {
                "name": "motherFullName",
                "required": true,
                "validation": {
                  "pattern": "^[a-zA-Z]+ [a-zA-Z]+$",
                  "message": "Name is not valid."
              }
              },
              {
                "name": "parentsMobileNumber",
                "required": true,
                "validation": {
                  "pattern": "[6-9]{1}[0-9]{9}",
                  "message": "Mobile Number must be 10 digit number."
                }
              },
              {
                "name": "sameAsAbove",
                "custom": true,
                "element": {
                    "title": "Same as above?",
                    "widget": {
                        "formlyConfig": {
                            "type": "checkbox",
                            "fieldGroupClassName": "controls",
                            "className": "checkbox",
                            "templateOptions": {
                                "required": true
                            }

                        }
                    }
                }
            },
              {
                "name": "parentsWhatsappNumber",
                "required": true,
                "validation": {
                  "pattern": "[6-9]{1}[0-9]{9}",
                  "message": "Mobile Number must be 10 digit number."

                },
                "expressionProperties": {
                  "templateOptions.disabled": "model.sameAsAbove",
                  "templateOptions.required": "!model.sameAsAbove"

                }
              },
              {
                "name": "mobileAvailablity",
                "required": true
              },

              {
                "name": "lastStandardOfEducation",
                "required": true
              },
              {
                "name": "lastStandardOfEducationYear",
                "required": true,
                "type": "date",
                "validation": {
                  "future": false
                }
              },
              {
                "name": "reasonOfLeavingEducation",
                "required": true
              },
              {
                "name": "whereStudiedLast",
                "required": true
              },
              {
                "name": "registrationStatus",
                "required": true
              },
              {
                "name": "AGDocumentsV2",
                "required": true
              }

            ]
          }
        ]
      }
    },
    {
      "ag-registration": {
        "api": "/AGV7",
        "type": "entity",
        "formclass": "row",
        "title": "Add new AG",
        "fieldsets": [
          {
            "definition": "AgRegistrationForm",
            "fields": [
              {
                "name": "isRSOS_NIOSFormSubmitted",
                "required": true
              },
              {
                "name": "RSOS_NIOSFormPhoto",
                "type": "file"
              },
              {
                "name": "examChoice",
                "required": true
              },
              {
                "name": "subjects",
                "required": true,
                "type": "multiselect",
                "title": "निम्न में से किशोरी द्वारा चुने गए विषय चुने",
                "validation": {
                  "max": 7,
                  "min":1
                }
              },
              {
                "name": "birthDateOnRSOS_NIOSForm",
                "required": true,
                "type":"date"
              },
              {
                "name": "isRSOS_NIOSRegIdReceived",
                "required": true
              },
              {
                "name": "RSOS_NIOSRegId",
                "required": true,
                "type": "number",
                "validation": {
                  "pattern": "^[0-9]*$",
                  "message": "Only numbers are allowed."
                }
              }

            ]
          }
        ],
        "redirectTo": "/profile/myags"
      }
    }
  ]
}
